---

---

> 进程：资源分配的基本单位
> 线程：程序执行的基本单位
>
> java程序默认线程：main线程，gc线程

### 锁升级

new-->无锁-->偏向锁-->轻量级-->重量级

等待的线程数量很大时，轻量级升级到重量级

#### 偏向锁



#### 轻量级锁

自旋锁

​	AtomicInteger

CAS(compareAndSwap)

```basic
lock cpmxchg; #汇编指令，保证操作的原子性
```



#### 重量级锁

进入等待队列，由操作系统进行调度

### 对象内存布局

JOL（java object layout）工具插件:

```xml
<!-- https://mvnrepository.com/artifact/org.openjdk.jol/jol-core -->
<dependency>
    <groupId>org.openjdk.jol</groupId>
    <artifactId>jol-core</artifactId>
    <version>0.14</version>
</dependency>
```

查看对象的内存布局

```java
public class Lock_01_jol {
    static final Object o = new Object();
    public static void main(String[] args) {
        System.out.println(ClassLayout.parseInstance(o).toPrintable());
        synchronized (o) {
            System.out.println(ClassLayout.parseInstance(o).toPrintable());
        }
    }
}
```

输出结果：

```properties
java.lang.Object object internals:
 OFFSET  SIZE   TYPE DESCRIPTION                               VALUE
      0     4        (object header)                           01 00 00 00 (00000001 00000000 00000000 00000000) (1)
      4     4        (object header)                           00 00 00 00 (00000000 00000000 00000000 00000000) (0)
      8     4        (object header)                           e5 01 00 f8 (11100101 00000001 00000000 11111000) (-134217243)
     12     4        (loss due to the next object alignment)
Instance size: 16 bytes
Space losses: 0 bytes internal + 4 bytes external = 4 bytes total

java.lang.Object object internals:
 OFFSET  SIZE   TYPE DESCRIPTION                               VALUE
      0     4        (object header)                           98 b9 07 0f (10011000 10111001 00000111 00001111) (252164504)
      4     4        (object header)                           00 70 00 00 (00000000 01110000 00000000 00000000) (28672)
      8     4        (object header)                           e5 01 00 f8 (11100101 00000001 00000000 11111000) (-134217243)
     12     4        (loss due to the next object alignment)
Instance size: 16 bytes
Space losses: 0 bytes internal + 4 bytes external = 4 bytes total
```

### 指令乱序

volatile

阻止指令乱序：添加内存屏障

```basic
asm volatile (lock addl ... )
```



### 对象的创建

#### 1静态变量对象

```properties
 0 new #7 <java/lang/Object>
 3 dup
 4 invokespecial #1 <java/lang/Object.<init>>
 7 putstatic #3 <cn/sharit/juc/_03lock/Lock_01_jol.o>
10 return
```

#### 2局部变量对象

```properties
 0 new #2 <java/lang/Object>
 3 dup
 4 invokespecial #1 <java/lang/Object.<init>>
 7 astore_1
 8 return
```

> 0 为对象申请内存空间；4 调用构造方法；7 将变量的引用指向申请的内存空间地址
>
> 4和7可能发生指令重排序

### DCL

```java
package cn.sharit.juc._03lock;

public class Lock_22_DCL {

    private Lock_22_DCL() {}

    private static volatile Lock_22_DCL INSTANCE; // volatile 线程可见性，禁止指令重排序

    public static Lock_22_DCL getInstance() {
        if (INSTANCE == null) {
            synchronized (Lock_22_DCL.class) {
                if (INSTANCE == null) {
                    try {
                        Thread.sleep(1);
                    } catch (InterruptedException e) {
                        e.printStackTrace();
                    }
                    INSTANCE = new Lock_22_DCL();
                }
            }
        }
        return INSTANCE;
    }

    public static void main(String[] args) {
        for (int i = 0; i < 10000; i++) {
            new Thread(() -> {
                System.out.println(getInstance().hashCode());
            }).start();
        }
    }

}
```



```java
try {
    TimeUnit.SECONDS.sleep(5);
} catch (InterruptedException e) {
    e.printStackTrace();
}
```

